{
  "name": "Soldier Ant",
  "category": "antsportation:entities",
  "icon": "antsportation:soldier_ant_spawn_egg",
  "pages": [
    {
      "type": "patchouli:entity",
      "name": "Soldier Ant",
      "entity":"antsportation:ant_soldier"
    },
    {
      "type": "patchouli:text",
      "text": "The Soldier ant is a cute lil' creature that'll try to bite off your toes to defend its colony.<br>Be careful, these creatures are a lot more dangerous than they might look!",
      "title": "Soldier Ant"
    }
  ]
}